{
  "LOOKBACK_SIGNAL": 84,
  "LOOKBACK_VOL": 63,
  "MOMENTUM_WINDOW": 126,
  "MOMENTUM_SKIP": 21,
  "MAX_CREDIT_ALLOC": 0.5,
  "MAX_TIP_ALLOC": 0.15,
  "MAX_ALT_ALLOC": 0.4,
  "SIGNAL_BLEND": 0.3,
  "VOL_TARGET": 0.08,
  "MAX_LEVERAGE": 1.5,
  "VIX_RISK_OFF": 25.0,
  "VIX_RISK_ON": 15.0,
  "DD_THRESHOLD": -0.05,
  "DD_SCALE": 0.0,
  "TRAILING_STOP_PCT": 0.04,
  "TRAILING_STOP_WINDOW": 21,
  "W_DURATION_2S10S": 0.2,
  "W_DURATION_10Y3M": 0.2,
  "W_DURATION_FED": 0.15,
  "W_DURATION_REALYLD": 0.25,
  "W_DURATION_LABOR": 0.1,
  "W_DURATION_ISM": 0.1,
  "W_CREDIT_HYOAS": 0.35,
  "W_CREDIT_IGMOM": 0.15,
  "W_CREDIT_VIX": 0.2,
  "W_CREDIT_FEDQT": 0.15,
  "W_CREDIT_TED": 0.15,
  "W_INFLATION_BEI": 0.5,
  "W_INFLATION_CPI": 0.5
}